msgraphfs/__init__.py
msgraphfs/core.py
msgraphfs-0.3.dist-info/METADATA
msgraphfs-0.3.dist-info/WHEEL
msgraphfs-0.3.dist-info/entry_points.txt
msgraphfs-0.3.dist-info/licenses/LICENSE
msgraphfs-0.3.dist-info/RECORD
